beatrica_git/__init__.py
beatrica_git/recent_change_inspector.py
beatrica_git-2025.5.180925.dist-info/licenses/LICENSE
tests/__init__.py
tests/test_recent_change_inspector.py
beatrica_git-2025.5.180925.dist-info/METADATA
beatrica_git-2025.5.180925.dist-info/WHEEL
beatrica_git-2025.5.180925.dist-info/top_level.txt
beatrica_git-2025.5.180925.dist-info/RECORD
